yellowbox_kind/__init__.py
yellowbox_kind/_version.py
yellowbox_kind/kind_cluster.py
yellowbox_kind/namespaces.py
yellowbox_kind-0.1.0.dist-info/METADATA
yellowbox_kind-0.1.0.dist-info/WHEEL
yellowbox_kind-0.1.0.dist-info/RECORD
