Metadata-Version: 2.1
Name: yellowbox-kind
Version: 0.1.0
Summary: 
Home-page: https://github.com/biocatchltd/yellowbox-kind
License: MIT
Author: biocatch ltd
Requires-Python: >=3.8,<4.0
Classifier: License :: OSI Approved :: MIT License
Classifier: Programming Language :: Python :: 3
Classifier: Programming Language :: Python :: 3.8
Classifier: Programming Language :: Python :: 3.9
Classifier: Programming Language :: Python :: 3.10
Classifier: Programming Language :: Python :: 3.11
Classifier: Programming Language :: Python :: 3.12
Requires-Dist: kubernetes (>=30.1.0,<31.0.0)
Requires-Dist: yellowbox (>=0.8.8,<0.9.0)
Project-URL: Repository, https://github.com/biocatchltd/yellowbox-kind
